setup.py
aidsinfo/__init__.py
aidsinfo/drug_info.py
aidsinfo.egg-info/PKG-INFO
aidsinfo.egg-info/SOURCES.txt
aidsinfo.egg-info/dependency_links.txt
aidsinfo.egg-info/top_level.txt
aidsinfo/api/__init__.py
aidsinfo/api/api.py
aidsinfo/api/test_api.py
aidsinfo/api/xml2dict/__init__.py
aidsinfo/api/xml2dict/object_dict.py
aidsinfo/api/xml2dict/xml2dict.py