Metadata-Version: 1.0
Name: aidsinfo
Version: 1.1
Summary: A Python wrapper for the AIDSinfo drug information API.
Home-page: https://github.com/zachwill/fred
Author: Zach Williams
Author-email: zach@codeforamerica.org
License: BSD
Keywords: aids,aids info,AIDSinfo,aidsinfo
Platform: UNKNOWN
Classifier: Development Status :: 5 - Production/Stable
Classifier: Intended Audience :: Developers
Classifier: Natural Language :: English
Classifier: Operating System :: OS Independent
Classifier: Programming Language :: Python :: 2
Classifier: Topic :: Internet
Classifier: Topic :: Internet :: WWW/HTTP
